calicode/__init__.py
calicode-0.0.0.dist-info/LICENSE
calicode-0.0.0.dist-info/METADATA
calicode-0.0.0.dist-info/WHEEL
calicode-0.0.0.dist-info/top_level.txt
calicode-0.0.0.dist-info/RECORD
